{
    "Description" : {
        "Id" : "tbone_event_co_interceptedcomms",
        "Name" : "Intercept Jade Falcon Communications",
        "Details" : "Play intercepted video",
        "Icon" : "uixTxrSpot_Store.png"
    },
    "Scope" : "Company",
    "Weight" : 10,
    "Requirements" : {
        "Scope" : "Company",
        "RequirementTags" : {
            "tagSetSourceFile" : "",
            "items" : []
        },
        "ExclusionTags" : {
            "tagSetSourceFile" : "",
            "items" : []
        },
        "RequirementComparisons" : []
    },
    "AdditionalRequirements" : [],
    "AdditionalObjects" : [],
    "Options" : [
        {
            "Description" : {
                "Id" : "outcome_0",
                "Name" : "Play video",
                "Details" : "Play video",
                "Icon" : null
            },
            "RequirementList" : [],
            "ResultSets" : [
                {
                    "Description" : {
                        "Id" : "outcome_0_0",
                        "Name" : "Play video",
                        "Details" : "Play video",
                        "Icon" : null
                    },
                    "Weight" : 100,
                    "Results" : [
                        {
                            "Scope" : "Company",
                            "Requirements" : null,
                            "AddedTags" : {
                                "tagSetSourceFile" : "",
                                "items" : []
                            },
                            "RemovedTags" : {
                                "tagSetSourceFile" : "",
                                "items" : []
                            },
                            "Stats" : null,
                            "Actions" : [
                                {
                                    "Type" : "System_PlayVideo",
                                    "value" : "interceptedcomms.bk2",
                                    "valueConstant" : null,
                                    "additionalValues" : null
                                }
                            ],
                            "ForceEvents" : null,
                            "TemporaryResult" : false,
                            "ResultDuration" : 0
                        }
                    ]
                }
            ],
            "Requirements" : {
                "Scope" : "Company",
                "RequirementTags" : {
                    "tagSetSourceFile" : "",
                    "items" : []
                },
                "ExclusionTags" : {
                    "tagSetSourceFile" : "",
                    "items" : []
                },
                "RequirementComparisons" : []
            }
        }
    ],
    "PublishState" : "PUBLISHED",
    "ValidationState" : "UNTESTED",
    "EventType" : "NORMAL",
    "OneTimeEvent" : true,
    "Tags" : {
        "tagSetSourceFile" : "tags/EventTags",
        "items" : []
    }
}